CHANGES.txt
LICENSE
MANIFEST.in
README.txt
setup.py
cronlib/__init__.py
cronlib.egg-info/PKG-INFO
cronlib.egg-info/SOURCES.txt
cronlib.egg-info/dependency_links.txt
cronlib.egg-info/not-zip-safe
cronlib.egg-info/top_level.txt
cronlib/vixie/CronJob.py
cronlib/vixie/CronSchedule.py
cronlib/vixie/CronTypes.py
cronlib/vixie/__init__.py