Metadata-Version: 1.0
Name: cronlib
Version: 0.1b
Summary: Interface to Unix/Linux Vixie Cron
Home-page: http://github.com/youshoulduseunix/cronlib
Author: Devin Cherry
Author-email: devincherry[at]gmail[dot]com
License: GNU LESSER GENERAL PUBLIC LICENSE, version 2.1
Platform: UNKNOWN
